{
  "project_info": {
    "project_number": "591223589431",
    "project_id": "sales-bets-79e8a",
    "storage_bucket": "sales-bets-79e8a.firebasestorage.app"
  },
  "client": [
    {
      "client_info": {
        "mobilesdk_app_id": "1:591223589431:android:9d51ca22187676c7b64db2",
        "android_client_info": {
          "package_name": "com.example.sales_bets"
        }
      },
      "oauth_client": [],
      "api_key": [
        {
          "current_key": "AIzaSyBCqtWVNuv8fO8khsZfqT6DxyTHGRLtEm0"
        }
      ],
      "services": {
        "appinvite_service": {
          "other_platform_oauth_client": []
        }
      }
    }
  ],
  "configuration_version": "1"
}